uart_protocol/uart_rx.v
module uart_rx(
input clk,
input rst,
input rx,
input baud16_tick,
output reg [7:0]rx_data,
output reg rx_done);

parameter idle   = 2'b00,
          start  = 2'b01,
          data   = 2'b10,
          stop   = 2'b11;

reg [1:0] state;
reg [7:0]shift_reg;
reg [2:0]bit_index;
reg [3:0]bit_count;

always@(posedge clk)begin
if(rst)begin
   rx_data   <= 8'd0;
   rx_done   <= 1'b0;
   state     <= idle;
   bit_index <= 3'd0;
   shift_reg <= 8'd0;
   bit_count <= 4'd0;
end
else begin
       rx_done <= 1'b0;

//idle state 

 if(state == idle)begin
    if(rx == 0)begin
      bit_count <=0;
      state     <= start;
     end
  end
else if(baud16_tick) begin
    case(state)
            start  : begin
		      if (bit_count == 7 ) begin
			  bit_count <= 0;
			  if (rx == 0)begin
		           bit_index <= 3'd0;
                           state     <= data;
		          end
                         else 
			    state <= idle;
		      end
		      else begin
			bit_count <= bit_count + 1;
                     end
	           end
       
            data   : begin
		       if(bit_count ==15)begin
                          bit_count <= 0;

                         shift_reg [bit_index] <= rx;

                         if(bit_index == 3'd7)
                           state <= stop;
		         else
                            bit_index <= bit_index + 3'd1;
	              end
		      else
			bit_count <= bit_count + 1;
	              
                     end

            stop : begin
		    if(bit_count == 15)begin
			bit_count <= 0;
                        
			if(rx == 1) begin
                          rx_data <= shift_reg;
                          rx_done <= 1'b1;
		       end
                        state   <= idle;
		    end
                    else
	             bit_count <= bit_count + 1;
	           
                 end
          default : state <= idle;

       endcase
     end
   end
 end
endmodule

uart_protocol/uart_tx.v
module uart_tx(
input clk,
input rst,
input tx_start,
input baud16_tick,
input [7:0] tx_data,
output reg tx,
output reg busy);

parameter idle   = 2'b00,
          start  = 2'b01,
          data   = 2'b10,
          stop   = 2'b11;

reg [7:0] shift_reg;
reg [1:0] state;
reg [2:0] bit_index;
reg [3:0] bit_count;

always@(posedge clk) begin
  if(rst)begin
      state     <= idle;
      tx        <= 1'd1;
      busy      <= 1'd0;
      shift_reg <= 8'd0;
      bit_index <= 3'd0;
      bit_count <= 4'b0;
  end
  else if(baud16_tick)begin
      
      case(state)
             idle  :  begin
                          tx        <= 1'b1;
                          busy      <= 1'b0;
			  bit_count <= 4'd0;

                        if(tx_start)begin
                           shift_reg <= tx_data;
                           busy      <= 1'b1;
                           bit_index <= 3'd0;
                           state     <= start;
                         end
		       end
                   
              start : begin
                           tx    <= 1'b0;
			    if(bit_count == 15) begin
	                        bit_count <= 4'd0;
                                state <= data;
			    end
                            else
			        bit_count <= bit_count + 1;
                       end
               
              data  : begin 
                           tx <= shift_reg[bit_index];
			    if(bit_count == 15) begin
	                       bit_count <= 4'd0;
                                                     
                             if(bit_index == 7)begin
                                state <= stop;
                             end

                             else
                               bit_index <= bit_index + 3'd1;
		             end
			   else
		            bit_count <= bit_count + 1;
                            
                      end
             
             stop  : begin
		      tx   <= 1'b1;

		      if(bit_count == 15) begin
	                  bit_count <= 4'd0;
                          busy      <= 1'b0;
                          state     <= idle;
                     end
		     else
			bit_count <= bit_count + 1;
		     end
		default : state <= idle;
             endcase
          end
       end    
endmodule

uart/baud_rate_generator.v
module baud_rate_generator #(
parameter clock_freq    = 50000000,
          baud_rate = 9600)(
input clk,
input rst,
output reg baud16_tick);

reg [15:0] counter;

localparam divisor = clock_freq /  (baud_rate * 16);

always@(posedge clk ) begin
if(rst)begin
   baud16_tick <= 0;
   counter     <= 0;
end
   else begin 
        if (counter == divisor - 1)begin
           counter     <= 0;
           baud16_tick <= 1;
        end
        else begin
            counter     <= counter + 1;
            baud16_tick <= 0;
    end
  end
 end
endmodule

uart_protocol/uart_top.v
module uart_top(
input clk,
input rst,

//tx
input tx_start,
input [7:0]tx_data,
output  tx,
output  busy,

//rx
input rx,
output  rx_done,
output  [7:0]rx_data);

wire baud_connect;

baud_rate_generator  #(.clock_freq(160),.baud_rate(10))dut1 (.clk(clk),.rst(rst),.baud16_tick(baud_connect));

uart_tx dut2 (.clk(clk),.rst(rst),.tx_start(tx_start),.tx_data(tx_data),.baud16_tick(baud_connect),.tx(tx),.busy(busy));

uart_rx dut3(.clk(clk),.rst(rst),.rx(rx),.baud16_tick(baud_connect),.rx_done(rx_done),.rx_data(rx_data));

endmodule

uart_protocol/uart_top_tb.v
module uart_top_tb;
reg clk;
reg rst;

//tx
reg tx_start;
reg[7:0]tx_data;
wire tx;
wire busy;

//rx
reg rx;
wire [7:0]rx_data;
wire rx_done;


uart_top dut (.clk(clk),.rst(rst),.tx_start(tx_start),.tx_data(tx_data),.tx(tx),.busy(busy),.rx(tx),.rx_data(rx_data),.rx_done(rx_done));

initial begin
clk=0;
forever #10 clk = ~clk;
end

initial begin
$display("simulation started");


$dumpfile("wave.vcd");
$dumpvars(0,uart_top_tb);

$monitor ("time=%0t clk=%b baud_tick=%b tx_state=%b rx_state=%b tx_start=%b tx_data=%b tx=%b send_bit=%b  busy=%b  rx=%b rx_data=%b rx_done=%b",$time,clk,dut.baud_connect,dut.dut2.state,dut.dut3.state,tx_start,tx_data,tx,dut.dut2.bit_index,dut.dut2.shift_reg,busy,rx,rx_data,rx_done);

#20;

clk=0;
rst=1;
tx_start=0;
tx_data=8'h0;
rx=0;
//data 1
#20;
rst=0;
@(posedge clk); 
tx_start=1;
tx_data=8'b11001011;
 
@(posedge clk);
tx_start=0;


wait(rx_done);

if(rx_data == 8'b11001011)
     $display("pass : received = %b ",rx_data);
else
     $display("fail : received = %b",rx_data);
wait(busy == 0);
#200;

//data 2
#10;
@(posedge clk); 
tx_start=1;
tx_data=8'b11001111;
 
@(posedge clk);
tx_start=0;


wait(rx_done);

if(rx_data == 8'b11001111)
     $display("pass : received = %b ",rx_data);
else
     $display("fail : received = %b",rx_data);
wait(busy == 0);
#100;
$finish;
end
endmodule

uart_protocol/wave.vcd
$date
	Tue Jul 14 09:40:14 2026
$end
$version
	Icarus Verilog
$end
$timescale
	1s
$end
$scope module uart_top_tb $end
$var wire 1 ! tx $end
$var wire 1 " rx_done $end
$var wire 8 # rx_data [7:0] $end
$var wire 1 $ busy $end
$var reg 1 % clk $end
$var reg 1 & rst $end
$var reg 1 ' rx $end
$var reg 8 ( tx_data [7:0] $end
$var reg 1 ) tx_start $end
$scope module dut $end
$var wire 1 % clk $end
$var wire 1 & rst $end
$var wire 8 * tx_data [7:0] $end
$var wire 1 ) tx_start $end
$var wire 1 ! tx $end
$var wire 1 " rx_done $end
$var wire 8 + rx_data [7:0] $end
$var wire 1 ! rx $end
$var wire 1 $ busy $end
$var wire 1 , baud_connect $end
$scope module dut1 $end
$var wire 1 % clk $end
$var wire 1 & rst $end
$var parameter 32 - baud_rate $end
$var parameter 32 . clock_freq $end
$var parameter 64 / divisor $end
$var reg 1 , baud16_tick $end
$var reg 16 0 counter [15:0] $end
$upscope $end
$scope module dut2 $end
$var wire 1 , baud16_tick $end
$var wire 1 % clk $end
$var wire 1 & rst $end
$var wire 8 1 tx_data [7:0] $end
$var wire 1 ) tx_start $end
$var parameter 2 2 data $end
$var parameter 2 3 idle $end
$var parameter 2 4 start $end
$var parameter 2 5 stop $end
$var reg 4 6 bit_count [3:0] $end
$var reg 3 7 bit_index [2:0] $end
$var reg 1 $ busy $end
$var reg 8 8 shift_reg [7:0] $end
$var reg 2 9 state [1:0] $end
$var reg 1 ! tx $end
$upscope $end
$scope module dut3 $end
$var wire 1 , baud16_tick $end
$var wire 1 % clk $end
$var wire 1 & rst $end
$var wire 1 ! rx $end
$var parameter 2 : data $end
$var parameter 2 ; idle $end
$var parameter 2 < start $end
$var parameter 2 = stop $end
$var reg 4 > bit_count [3:0] $end
$var reg 3 ? bit_index [2:0] $end
$var reg 8 @ rx_data [7:0] $end
$var reg 1 " rx_done $end
$var reg 8 A shift_reg [7:0] $end
$var reg 2 B state [1:0] $end
$upscope $end
$upscope $end
$upscope $end
$enddefinitions $end
$comment Show the parameter values. $end
$dumpall
b11 =
b1 <
b0 ;
b10 :
b11 5
b1 4
b0 3
b10 2
b1 /
b10100000 .
b1010 -
$end
#0
$dumpvars
bx B
bx A
bx @
bx ?
bx >
bx 9
bx 8
bx 7
bx 6
bx 1
bx 0
x,
bx +
bx *
x)
bx (
x'
x&
0%
x$
bx #
x"
x!
$end
#10
0,
0"
1%
#20
b0 >
b0 A
b0 ?
b0 B
b0 #
b0 +
b0 @
b0 6
b0 7
b0 8
0$
1!
b0 9
b0 0
0'
b0 (
b0 *
b0 1
0)
1&
1%
#30
0%
#40
1,
b11001011 (
b11001011 *
b11001011 1
1)
1%
0&
#50
0%
#60
b1 9
1$
b11001011 8
0)
1%
#70
0%
#80
b1 6
0!
1%
#90
0%
#100
b1 B
b10 6
1%
#110
0%
#120
b11 6
b1 >
1%
#130
0%
#140
b10 >
b100 6
1%
#150
0%
#160
b101 6
b11 >
1%
#170
0%
#180
b100 >
b110 6
1%
#190
0%
#200
b111 6
b101 >
1%
#210
0%
#220
b110 >
b1000 6
1%
#230
0%
#240
b1001 6
b111 >
1%
#250
0%
#260
b10 B
b0 >
b1010 6
1%
#270
0%
#280
b1011 6
b1 >
1%
#290
0%
#300
b10 >
b1100 6
1%
#310
0%
#320
b1101 6
b11 >
1%
#330
0%
#340
b100 >
b1110 6
1%
#350
0%
#360
b1111 6
b101 >
1%
#370
0%
#380
b110 >
b10 9
b0 6
1%
#390
0%
#400
b1 6
1!
b111 >
1%
#410
0%
#420
b1000 >
b10 6
1%
#430
0%
#440
b11 6
b1001 >
1%
#450
0%
#460
b1010 >
b100 6
1%
#470
0%
#480
b101 6
b1011 >
1%
#490
0%
#500
b1100 >
b110 6
1%
#510
0%
#520
b111 6
b1101 >
1%
#530
0%
#540
b1110 >
b1000 6
1%
#550
0%
#560
b1001 6
b1111 >
1%
#570
0%
#580
b1 ?
b1 A
b0 >
b1010 6
1%
#590
0%
#600
b1011 6
b1 >
1%
#610
0%
#620
b10 >
b1100 6
1%
#630
0%
#640
b1101 6
b11 >
1%
#650
0%
#660
b100 >
b1110 6
1%
#670
0%
#680
b1111 6
b101 >
1%
#690
0%
#700
b110 >
b1 7
b0 6
1%
#710
0%
#720
b1 6
b111 >
1%
#730
0%
#740
b1000 >
b10 6
1%
#750
0%
#760
b11 6
b1001 >
1%
#770
0%
#780
b1010 >
b100 6
1%
#790
0%
#800
b101 6
b1011 >
1%
#810
0%
#820
b1100 >
b110 6
1%
#830
0%
#840
b111 6
b1101 >
1%
#850
0%
#860
b1110 >
b1000 6
1%
#870
0%
#880
b1001 6
b1111 >
1%
#890
0%
#900
b10 ?
b11 A
b0 >
b1010 6
1%
#910
0%
#920
b1011 6
b1 >
1%
#930
0%
#940
b10 >
b1100 6
1%
#950
0%
#960
b1101 6
b11 >
1%
#970
0%
#980
b100 >
b1110 6
1%
#990
0%
#1000
b1111 6
b101 >
1%
#1010
0%
#1020
b110 >
b10 7
b0 6
1%
#1030
0%
#1040
b1 6
0!
b111 >
1%
#1050
0%
#1060
b1000 >
b10 6
1%
#1070
0%
#1080
b11 6
b1001 >
1%
#1090
0%
#1100
b1010 >
b100 6
1%
#1110
0%
#1120
b101 6
b1011 >
1%
#1130
0%
#1140
b1100 >
b110 6
1%
#1150
0%
#1160
b111 6
b1101 >
1%
#1170
0%
#1180
b1110 >
b1000 6
1%
#1190
0%
#1200
b1001 6
b1111 >
1%
#1210
0%
#1220
b11 ?
b0 >
b1010 6
1%
#1230
0%
#1240
b1011 6
b1 >
1%
#1250
0%
#1260
b10 >
b1100 6
1%
#1270
0%
#1280
b1101 6
b11 >
1%
#1290
0%
#1300
b100 >
b1110 6
1%
#1310
0%
#1320
b1111 6
b101 >
1%
#1330
0%
#1340
b110 >
b11 7
b0 6
1%
#1350
0%
#1360
b1 6
1!
b111 >
1%
#1370
0%
#1380
b1000 >
b10 6
1%
#1390
0%
#1400
b11 6
b1001 >
1%
#1410
0%
#1420
b1010 >
b100 6
1%
#1430
0%
#1440
b101 6
b1011 >
1%
#1450
0%
#1460
b1100 >
b110 6
1%
#1470
0%
#1480
b111 6
b1101 >
1%
#1490
0%
#1500
b1110 >
b1000 6
1%
#1510
0%
#1520
b1001 6
b1111 >
1%
#1530
0%
#1540
b100 ?
b1011 A
b0 >
b1010 6
1%
#1550
0%
#1560
b1011 6
b1 >
1%
#1570
0%
#1580
b10 >
b1100 6
1%
#1590
0%
#1600
b1101 6
b11 >
1%
#1610
0%
#1620
b100 >
b1110 6
1%
#1630
0%
#1640
b1111 6
b101 >
1%
#1650
0%
#1660
b110 >
b100 7
b0 6
1%
#1670
0%
#1680
b1 6
0!
b111 >
1%
#1690
0%
#1700
b1000 >
b10 6
1%
#1710
0%
#1720
b11 6
b1001 >
1%
#1730
0%
#1740
b1010 >
b100 6
1%
#1750
0%
#1760
b101 6
b1011 >
1%
#1770
0%
#1780
b1100 >
b110 6
1%
#1790
0%
#1800
b111 6
b1101 >
1%
#1810
0%
#1820
b1110 >
b1000 6
1%
#1830
0%
#1840
b1001 6
b1111 >
1%
#1850
0%
#1860
b101 ?
b0 >
b1010 6
1%
#1870
0%
#1880
b1011 6
b1 >
1%
#1890
0%
#1900
b10 >
b1100 6
1%
#1910
0%
#1920
b1101 6
b11 >
1%
#1930
0%
#1940
b100 >
b1110 6
1%
#1950
0%
#1960
b1111 6
b101 >
1%
#1970
0%
#1980
b110 >
b101 7
b0 6
1%
#1990
0%
#2000
b1 6
b111 >
1%
#2010
0%
#2020
b1000 >
b10 6
1%
#2030
0%
#2040
b11 6
b1001 >
1%
#2050
0%
#2060
b1010 >
b100 6
1%
#2070
0%
#2080
b101 6
b1011 >
1%
#2090
0%
#2100
b1100 >
b110 6
1%
#2110
0%
#2120
b111 6
b1101 >
1%
#2130
0%
#2140
b1110 >
b1000 6
1%
#2150
0%
#2160
b1001 6
b1111 >
1%
#2170
0%
#2180
b110 ?
b0 >
b1010 6
1%
#2190
0%
#2200
b1011 6
b1 >
1%
#2210
0%
#2220
b10 >
b1100 6
1%
#2230
0%
#2240
b1101 6
b11 >
1%
#2250
0%
#2260
b100 >
b1110 6
1%
#2270
0%
#2280
b1111 6
b101 >
1%
#2290
0%
#2300
b110 >
b110 7
b0 6
1%
#2310
0%
#2320
b1 6
1!
b111 >
1%
#2330
0%
#2340
b1000 >
b10 6
1%
#2350
0%
#2360
b11 6
b1001 >
1%
#2370
0%
#2380
b1010 >
b100 6
1%
#2390
0%
#2400
b101 6
b1011 >
1%
#2410
0%
#2420
b1100 >
b110 6
1%
#2430
0%
#2440
b111 6
b1101 >
1%
#2450
0%
#2460
b1110 >
b1000 6
1%
#2470
0%
#2480
b1001 6
b1111 >
1%
#2490
0%
#2500
b111 ?
b1001011 A
b0 >
b1010 6
1%
#2510
0%
#2520
b1011 6
b1 >
1%
#2530
0%
#2540
b10 >
b1100 6
1%
#2550
0%
#2560
b1101 6
b11 >
1%
#2570
0%
#2580
b100 >
b1110 6
1%
#2590
0%
#2600
b1111 6
b101 >
1%
#2610
0%
#2620
b110 >
b111 7
b0 6
1%
#2630
0%
#2640
b1 6
b111 >
1%
#2650
0%
#2660
b1000 >
b10 6
1%
#2670
0%
#2680
b11 6
b1001 >
1%
#2690
0%
#2700
b1010 >
b100 6
1%
#2710
0%
#2720
b101 6
b1011 >
1%
#2730
0%
#2740
b1100 >
b110 6
1%
#2750
0%
#2760
b111 6
b1101 >
1%
#2770
0%
#2780
b1110 >
b1000 6
1%
#2790
0%
#2800
b1001 6
b1111 >
1%
#2810
0%
#2820
b11 B
b11001011 A
b0 >
b1010 6
1%
#2830
0%
#2840
b1011 6
b1 >
1%
#2850
0%
#2860
b10 >
b1100 6
1%
#2870
0%
#2880
b1101 6
b11 >
1%
#2890
0%
#2900
b100 >
b1110 6
1%
#2910
0%
#2920
b1111 6
b101 >
1%
#2930
0%
#2940
b110 >
b11 9
b0 6
1%
#2950
0%
#2960
b1 6
b111 >
1%
#2970
0%
#2980
b1000 >
b10 6
1%
#2990
0%
#3000
b11 6
b1001 >
1%
#3010
0%
#3020
b1010 >
b100 6
1%
#3030
0%
#3040
b101 6
b1011 >
1%
#3050
0%
#3060
b1100 >
b110 6
1%
#3070
0%
#3080
b111 6
b1101 >
1%
#3090
0%
#3100
b1110 >
b1000 6
1%
#3110
0%
#3120
b1001 6
b1111 >
1%
#3130
0%
#3140
b0 B
1"
b11001011 #
b11001011 +
b11001011 @
b0 >
b1010 6
1%
#3150
0%
#3160
b1011 6
0"
1%
#3170
0%
#3180
b1100 6
1%
#3190
0%
#3200
b1101 6
1%
#3210
0%
#3220
b1110 6
1%
#3230
0%
#3240
b1111 6
1%
#3250
0%
#3260
b0 9
0$
b0 6
1%
#3270
0%
#3280
1%
#3290
0%
#3300
1%
#3310
0%
#3320
1%
#3330
0%
#3340
1%
#3350
0%
#3360
1%
#3370
0%
#3380
1%
#3390
0%
#3400
1%
#3410
0%
#3420
1%
#3430
0%
#3440
1%
#3450
0%
#3460
1%
#3470
0%
#3480
b1 9
b0 7
1$
b11001111 8
b11001111 (
b11001111 *
b11001111 1
1)
1%
#3490
0%
#3500
b1 6
0!
0)
1%
#3510
0%
#3520
b10 6
b1 B
1%
#3530
0%
#3540
b1 >
b11 6
1%
#3550
0%
#3560
b100 6
b10 >
1%
#3570
0%
#3580
b11 >
b101 6
1%
#3590
0%
#3600
b110 6
b100 >
1%
#3610
0%
#3620
b101 >
b111 6
1%
#3630
0%
#3640
b1000 6
b110 >
1%
#3650
0%
#3660
b111 >
b1001 6
1%
#3670
0%
#3680
b1010 6
b10 B
b0 ?
b0 >
1%
#3690
0%
#3700
b1 >
b1011 6
1%
#3710
0%
#3720
b1100 6
b10 >
1%
#3730
0%
#3740
b11 >
b1101 6
1%
#3750
0%
#3760
b1110 6
b100 >
1%
#3770
0%
#3780
b101 >
b1111 6
1%
#3790
0%
#3800
b10 9
b0 6
b110 >
1%
#3810
0%
#3820
b111 >
b1 6
1!
1%
#3830
0%
#3840
b10 6
b1000 >
1%
#3850
0%
#3860
b1001 >
b11 6
1%
#3870
0%
#3880
b100 6
b1010 >
1%
#3890
0%
#3900
b1011 >
b101 6
1%
#3910
0%
#3920
b110 6
b1100 >
1%
#3930
0%
#3940
b1101 >
b111 6
1%
#3950
0%
#3960
b1000 6
b1110 >
1%
#3970
0%
#3980
b1111 >
b1001 6
1%
#3990
0%
#4000
b1010 6
b1 ?
b0 >
1%
#4010
0%
#4020
b1 >
b1011 6
1%
#4030
0%
#4040
b1100 6
b10 >
1%
#4050
0%
#4060
b11 >
b1101 6
1%
#4070
0%
#4080
b1110 6
b100 >
1%
#4090
0%
#4100
b101 >
b1111 6
1%
#4110
0%
#4120
b1 7
b0 6
b110 >
1%
#4130
0%
#4140
b111 >
b1 6
1%
#4150
0%
#4160
b10 6
b1000 >
1%
#4170
0%
#4180
b1001 >
b11 6
1%
#4190
0%
#4200
b100 6
b1010 >
1%
#4210
0%
#4220
b1011 >
b101 6
1%
#4230
0%
#4240
b110 6
b1100 >
1%
#4250
0%
#4260
b1101 >
b111 6
1%
#4270
0%
#4280
b1000 6
b1110 >
1%
#4290
0%
#4300
b1111 >
b1001 6
1%
#4310
0%
#4320
b1010 6
b10 ?
b0 >
1%
#4330
0%
#4340
b1 >
b1011 6
1%
#4350
0%
#4360
b1100 6
b10 >
1%
#4370
0%
#4380
b11 >
b1101 6
1%
#4390
0%
#4400
b1110 6
b100 >
1%
#4410
0%
#4420
b101 >
b1111 6
1%
#4430
0%
#4440
b10 7
b0 6
b110 >
1%
#4450
0%
#4460
b111 >
b1 6
1%
#4470
0%
#4480
b10 6
b1000 >
1%
#4490
0%
#4500
b1001 >
b11 6
1%
#4510
0%
#4520
b100 6
b1010 >
1%
#4530
0%
#4540
b1011 >
b101 6
1%
#4550
0%
#4560
b110 6
b1100 >
1%
#4570
0%
#4580
b1101 >
b111 6
1%
#4590
0%
#4600
b1000 6
b1110 >
1%
#4610
0%
#4620
b1111 >
b1001 6
1%
#4630
0%
#4640
b1010 6
b11 ?
b11001111 A
b0 >
1%
#4650
0%
#4660
b1 >
b1011 6
1%
#4670
0%
#4680
b1100 6
b10 >
1%
#4690
0%
#4700
b11 >
b1101 6
1%
#4710
0%
#4720
b1110 6
b100 >
1%
#4730
0%
#4740
b101 >
b1111 6
1%
#4750
0%
#4760
b11 7
b0 6
b110 >
1%
#4770
0%
#4780
b111 >
b1 6
1%
#4790
0%
#4800
b10 6
b1000 >
1%
#4810
0%
#4820
b1001 >
b11 6
1%
#4830
0%
#4840
b100 6
b1010 >
1%
#4850
0%
#4860
b1011 >
b101 6
1%
#4870
0%
#4880
b110 6
b1100 >
1%
#4890
0%
#4900
b1101 >
b111 6
1%
#4910
0%
#4920
b1000 6
b1110 >
1%
#4930
0%
#4940
b1111 >
b1001 6
1%
#4950
0%
#4960
b1010 6
b100 ?
b0 >
1%
#4970
0%
#4980
b1 >
b1011 6
1%
#4990
0%
#5000
b1100 6
b10 >
1%
#5010
0%
#5020
b11 >
b1101 6
1%
#5030
0%
#5040
b1110 6
b100 >
1%
#5050
0%
#5060
b101 >
b1111 6
1%
#5070
0%
#5080
b100 7
b0 6
b110 >
1%
#5090
0%
#5100
b111 >
b1 6
0!
1%
#5110
0%
#5120
b10 6
b1000 >
1%
#5130
0%
#5140
b1001 >
b11 6
1%
#5150
0%
#5160
b100 6
b1010 >
1%
#5170
0%
#5180
b1011 >
b101 6
1%
#5190
0%
#5200
b110 6
b1100 >
1%
#5210
0%
#5220
b1101 >
b111 6
1%
#5230
0%
#5240
b1000 6
b1110 >
1%
#5250
0%
#5260
b1111 >
b1001 6
1%
#5270
0%
#5280
b1010 6
b101 ?
b0 >
1%
#5290
0%
#5300
b1 >
b1011 6
1%
#5310
0%
#5320
b1100 6
b10 >
1%
#5330
0%
#5340
b11 >
b1101 6
1%
#5350
0%
#5360
b1110 6
b100 >
1%
#5370
0%
#5380
b101 >
b1111 6
1%
#5390
0%
#5400
b101 7
b0 6
b110 >
1%
#5410
0%
#5420
b111 >
b1 6
1%
#5430
0%
#5440
b10 6
b1000 >
1%
#5450
0%
#5460
b1001 >
b11 6
1%
#5470
0%
#5480
b100 6
b1010 >
1%
#5490
0%
#5500
b1011 >
b101 6
1%
#5510
0%
#5520
b110 6
b1100 >
1%
#5530
0%
#5540
b1101 >
b111 6
1%
#5550
0%
#5560
b1000 6
b1110 >
1%
#5570
0%
#5580
b1111 >
b1001 6
1%
#5590
0%
#5600
b1010 6
b110 ?
b0 >
1%
#5610
0%
#5620
b1 >
b1011 6
1%
#5630
0%
#5640
b1100 6
b10 >
1%
#5650
0%
#5660
b11 >
b1101 6
1%
#5670
0%
#5680
b1110 6
b100 >
1%
#5690
0%
#5700
b101 >
b1111 6
1%
#5710
0%
#5720
b110 7
b0 6
b110 >
1%
#5730
0%
#5740
b111 >
b1 6
1!
1%
#5750
0%
#5760
b10 6
b1000 >
1%
#5770
0%
#5780
b1001 >
b11 6
1%
#5790
0%
#5800
b100 6
b1010 >
1%
#5810
0%
#5820
b1011 >
b101 6
1%
#5830
0%
#5840
b110 6
b1100 >
1%
#5850
0%
#5860
b1101 >
b111 6
1%
#5870
0%
#5880
b1000 6
b1110 >
1%
#5890
0%
#5900
b1111 >
b1001 6
1%
#5910
0%
#5920
b1010 6
b111 ?
b0 >
1%
#5930
0%
#5940
b1 >
b1011 6
1%
#5950
0%
#5960
b1100 6
b10 >
1%
#5970
0%
#5980
b11 >
b1101 6
1%
#5990
0%
#6000
b1110 6
b100 >
1%
#6010
0%
#6020
b101 >
b1111 6
1%
#6030
0%
#6040
b111 7
b0 6
b110 >
1%
#6050
0%
#6060
b111 >
b1 6
1%
#6070
0%
#6080
b10 6
b1000 >
1%
#6090
0%
#6100
b1001 >
b11 6
1%
#6110
0%
#6120
b100 6
b1010 >
1%
#6130
0%
#6140
b1011 >
b101 6
1%
#6150
0%
#6160
b110 6
b1100 >
1%
#6170
0%
#6180
b1101 >
b111 6
1%
#6190
0%
#6200
b1000 6
b1110 >
1%
#6210
0%
#6220
b1111 >
b1001 6
1%
#6230
0%
#6240
b1010 6
b11 B
b0 >
1%
#6250
0%
#6260
b1 >
b1011 6
1%
#6270
0%
#6280
b1100 6
b10 >
1%
#6290
0%
#6300
b11 >
b1101 6
1%
#6310
0%
#6320
b1110 6
b100 >
1%
#6330
0%
#6340
b101 >
b1111 6
1%
#6350
0%
#6360
b11 9
b0 6
b110 >
1%
#6370
0%
#6380
b111 >
b1 6
1%
#6390
0%
#6400
b10 6
b1000 >
1%
#6410
0%
#6420
b1001 >
b11 6
1%
#6430
0%
#6440
b100 6
b1010 >
1%
#6450
0%
#6460
b1011 >
b101 6
1%
#6470
0%
#6480
b110 6
b1100 >
1%
#6490
0%
#6500
b1101 >
b111 6
1%
#6510
0%
#6520
b1000 6
b1110 >
1%
#6530
0%
#6540
b1111 >
b1001 6
1%
#6550
0%
#6560
b1010 6
b0 B
1"
b11001111 #
b11001111 +
b11001111 @
b0 >
1%
#6570
0%
#6580
0"
b1011 6
1%
#6590
0%
#6600
b1100 6
1%
#6610
0%
#6620
b1101 6
1%
#6630
0%
#6640
b1110 6
1%
#6650
0%
#6660
b1111 6
1%
#6670
0%
#6680
b0 9
0$
b0 6
1%
