uart_protocol/uart_rx.v
module uart_rx(
input clk,
input rst,
input rx,
input baud16_tick,
output reg [7:0]rx_data,
output reg rx_done);

parameter idle   = 2'b00,
          start  = 2'b01,
          data   = 2'b10,
          stop   = 2'b11;

reg [1:0] state;
reg [7:0]shift_reg;
reg [2:0]bit_index;
reg [3:0]bit_count;

always@(posedge clk)begin
if(rst)begin
   rx_data   <= 8'd0;
   rx_done   <= 1'b0;
   state     <= idle;
   bit_index <= 3'd0;
   shift_reg <= 8'd0;
   bit_count <= 4'd0;
end
else begin
       rx_done <= 1'b0;

//idle state 

 if(state == idle)begin
    if(rx == 0)begin
      bit_count <=0;
      state     <= start;
     end
  end
else if(baud16_tick) begin
    case(state)
            start  : begin
		      if (bit_count == 7 ) begin
			  bit_count <= 0;
			  if (rx == 0)begin
		           bit_index <= 3'd0;
                           state     <= data;
		          end
                         else 
			    state <= idle;
		      end
		      else begin
			bit_count <= bit_count + 1;
                     end
	           end
       
            data   : begin
		       if(bit_count ==15)begin
                          bit_count <= 0;

                         shift_reg [bit_index] <= rx;

                         if(bit_index == 3'd7)
                           state <= stop;
		         else
                            bit_index <= bit_index + 3'd1;
	              end
		      else
			bit_count <= bit_count + 1;
	              
                     end

            stop : begin
		    if(bit_count == 15)begin
			bit_count <= 0;
                        
			if(rx == 1) begin
                          rx_data <= shift_reg;
                          rx_done <= 1'b1;
		       end
                        state   <= idle;
		    end
                    else
	             bit_count <= bit_count + 1;
	           
                 end
          default : state <= idle;

       endcase
     end
   end
 end
endmodule

uart/uart_tx.v
module uart_tx(
input clk,
input rst,
input tx_start,
input baud16_tick,
input [7:0] tx_data,
output reg tx,
output reg busy);

parameter idle   = 2'b00,
          start  = 2'b01,
          data   = 2'b10,
          stop   = 2'b11;

reg [7:0] shift_reg;
reg [1:0] state;
reg [2:0] bit_index;
reg [3:0] bit_count;

always@(posedge clk) begin
  if(rst)begin
      state     <= idle;
      tx        <= 1'd1;
      busy      <= 1'd0;
      shift_reg <= 8'd0;
      bit_index <= 3'd0;
      bit_count <= 4'b0;
  end
  else begin
      
      case(state)
             idle  :  begin
                          tx        <= 1'b1;
                          busy      <= 1'b0;
			  bit_count <= 4'd0;

                        if(tx_start)begin
                           shift_reg <= tx_data;
                           busy      <= 1'b1;
                           bit_index <= 3'd0;
                           state     <= start;
                         end
		       end
                   
              start : begin
                           tx    <= 1'b0;
			   if(baud16_tick)begin
			    if(bit_count == 15) begin
	                        bit_count <= 4'd0;
                                state <= data;
			    end
                            else
			        bit_count <= bit_count + 1;
		        end
                       end
               
              data  : begin 
                           tx <= shift_reg[bit_index];

			   if(baud16_tick)begin
			    if(bit_count == 15) begin
	                       bit_count <= 4'd0;
                                                     
                             if(bit_index == 3'd7)
                                state <= stop;
                             

                             else
                               bit_index <= bit_index + 3'd1;
		             end
			   else
		            bit_count <= bit_count + 1;
		       end
                      end
             
             stop  : begin
		      tx   <= 1'b1;
                       
		    if(baud16_tick)begin
		      if(bit_count == 15) begin
	                  bit_count <= 4'd0;
                          busy      <= 1'b0;
                          state     <= idle;
                     end
		     else
			bit_count <= bit_count + 1;
		     end
	            end
		default : state <= idle;
             endcase
          end
       end    
endmodule

uart/baud_rate_generator.v
module baud_rate_generator #(
parameter clock_freq    = 50000000,
          baud_rate = 9600)(
input clk,
input rst,
output reg baud16_tick);

reg [15:0] counter;

localparam divisor = clock_freq /  (baud_rate * 16);

always@(posedge clk ) begin
if(rst)begin
   baud16_tick <= 0;
   counter     <= 0;
end
   else begin 
        if (counter == divisor - 1)begin
           counter     <= 0;
           baud16_tick <= 1;
        end
        else begin
            counter     <= counter + 1;
            baud16_tick <= 0;
    end
  end
 end
endmodule

uart/uart_top.v
module uart_top(
input clk,
input rst,

//tx
input tx_start,
input [7:0]tx_data,
output  tx,
output  busy,

//rx
input rx,
output  rx_done,
output  [7:0]rx_data);

wire baud_connect;

baud_rate_generator  #(.clock_freq(50000000),.baud_rate(9600))dut1 (.clk(clk),.rst(rst),.baud16_tick(baud_connect));

uart_tx dut2 (.clk(clk),.rst(rst),.tx_start(tx_start),.tx_data(tx_data),.baud16_tick(baud_connect),.tx(tx),.busy(busy));

uart_rx dut3(.clk(clk),.rst(rst),.rx(rx),.baud16_tick(baud_connect),.rx_done(rx_done),.rx_data(rx_data));

endmodule

uart/uart_top_tb.v
module uart_top_tb;
reg clk;
reg rst;

//tx
reg tx_start;
reg[7:0]tx_data;
wire tx;
wire busy;

//rx
reg rx;
wire [7:0]rx_data;
wire rx_done;


uart_top dut (.clk(clk),.rst(rst),.tx_start(tx_start),.tx_data(tx_data),.tx(tx),.busy(busy),.rx(tx),.rx_data(rx_data),.rx_done(rx_done));

initial begin
clk=0;
forever #10 clk = ~clk;
end

initial begin
$display("simulation started");


$dumpfile("wave.vcd");
$dumpvars(0,uart_top_tb);

#20;

clk=0;
rst=1;
tx_start=0;
tx_data=8'h0;
rx=0;
//data 1
#20;
rst=0;
@(posedge clk); 
tx_data=8'b11001011;
tx_start=1;

$display("Waiting for busy...");
wait(busy ==1);
$display("TX started.");

@(posedge clk);
tx_start=0;

$display("waiting for rx_done...");
wait(rx_done);
$display("rx done.");

if(rx_data == 8'b11001011)
     $display("pass : received = %b ",rx_data);
else
     $display("fail : received = %b",rx_data);
wait(busy == 0);
#200;

//data 2
#10;
@(posedge clk); 
tx_data=8'b11001111;
tx_start=1;

wait(busy ==1);

@(posedge clk);
tx_start=0;


wait(rx_done);

if(rx_data == 8'b11001111)
     $display("pass : received = %b ",rx_data);
else
     $display("fail : received = %b",rx_data);
wait(busy == 0);
#100;
$finish;
end
endmodule

uart/wave.vcd
$date
	Sat Jul 18 10:12:14 2026
$end
$version
	Icarus Verilog
$end
$timescale
	1s
$end
$scope module uart_top_tb $end
$var wire 1 ! tx $end
$var wire 1 " rx_done $end
$var wire 8 # rx_data [7:0] $end
$var wire 1 $ busy $end
$var reg 1 % clk $end
$var reg 1 & rst $end
$var reg 1 ' rx $end
$var reg 8 ( tx_data [7:0] $end
$var reg 1 ) tx_start $end
$scope module dut $end
$var wire 1 % clk $end
$var wire 1 & rst $end
$var wire 8 * tx_data [7:0] $end
$var wire 1 ) tx_start $end
$var wire 1 ! tx $end
$var wire 1 " rx_done $end
$var wire 8 + rx_data [7:0] $end
$var wire 1 ! rx $end
$var wire 1 $ busy $end
$var wire 1 , baud_connect $end
$scope module dut1 $end
$var wire 1 % clk $end
$var wire 1 & rst $end
$var parameter 32 - baud_rate $end
$var parameter 32 . clock_freq $end
$var parameter 64 / divisor $end
$var reg 1 , baud16_tick $end
$var reg 16 0 counter [15:0] $end
$upscope $end
$scope module dut2 $end
$var wire 1 , baud16_tick $end
$var wire 1 % clk $end
$var wire 1 & rst $end
$var wire 8 1 tx_data [7:0] $end
$var wire 1 ) tx_start $end
$var parameter 2 2 data $end
$var parameter 2 3 idle $end
$var parameter 2 4 start $end
$var parameter 2 5 stop $end
$var reg 4 6 bit_count [3:0] $end
$var reg 3 7 bit_index [2:0] $end
$var reg 1 $ busy $end
$var reg 8 8 shift_reg [7:0] $end
$var reg 2 9 state [1:0] $end
$var reg 1 ! tx $end
$upscope $end
$scope module dut3 $end
$var wire 1 , baud16_tick $end
$var wire 1 % clk $end
$var wire 1 & rst $end
$var wire 1 ! rx $end
$var parameter 2 : data $end
$var parameter 2 ; idle $end
$var parameter 2 < start $end
$var parameter 2 = stop $end
$var reg 4 > bit_count [3:0] $end
$var reg 3 ? bit_index [2:0] $end
$var reg 8 @ rx_data [7:0] $end
$var reg 1 " rx_done $end
$var reg 8 A shift_reg [7:0] $end
$var reg 2 B state [1:0] $end
$upscope $end
$upscope $end
$upscope $end
$enddefinitions $end
$comment Show the parameter values. $end
$dumpall
b11 =
b1 <
b0 ;
b10 :
b11 5
b1 4
b0 3
b10 2
b101000101 /
b10111110101111000010000000 .
b10010110000000 -
$end
#0
$dumpvars
bx B
bx A
bx @
bx ?
bx >
bx 9
bx 8
bx 7
bx 6
bx 1
bx 0
x,
bx +
bx *
x)
bx (
x'
x&
0%
x$
bx #
x"
x!
$end
#10
0,
b0 9
0"
1%
#20
b0 >
b0 A
b0 ?
b0 B
b0 #
b0 +
b0 @
b0 6
b0 7
b0 8
0$
1!
b0 0
0'
b0 (
b0 *
b0 1
0)
1&
1%
#30
0%
#40
b1 0
b1 9
1$
b11001011 8
1)
b11001011 (
b11001011 *
b11001011 1
1%
0&
#50
0%
#60
0!
b10 0
0)
1%
#70
0%
#80
b11 0
b1 B
1%
#90
0%
#100
b100 0
1%
#110
0%
#120
b101 0
1%
#130
0%
#140
b110 0
1%
#150
0%
#160
b111 0
1%
#170
0%
#180
b1000 0
1%
#190
0%
#200
b1001 0
1%
#210
0%
#220
b1010 0
1%
#230
0%
#240
b1011 0
1%
#250
0%
#260
b1100 0
1%
#270
0%
#280
b1101 0
1%
#290
0%
#300
b1110 0
1%
#310
0%
#320
b1111 0
1%
#330
0%
#340
b10000 0
1%
#350
0%
#360
b10001 0
1%
#370
0%
#380
b10010 0
1%
#390
0%
#400
b10011 0
1%
#410
0%
#420
b10100 0
1%
#430
0%
#440
b10101 0
1%
#450
0%
#460
b10110 0
1%
#470
0%
#480
b10111 0
1%
#490
0%
#500
b11000 0
1%
#510
0%
#520
b11001 0
1%
#530
0%
#540
b11010 0
1%
#550
0%
#560
b11011 0
1%
#570
0%
#580
b11100 0
1%
#590
0%
#600
b11101 0
1%
#610
0%
#620
b11110 0
1%
#630
0%
#640
b11111 0
1%
#650
0%
#660
b100000 0
1%
#670
0%
#680
b100001 0
1%
#690
0%
#700
b100010 0
1%
#710
0%
#720
b100011 0
1%
#730
0%
#740
b100100 0
1%
#750
0%
#760
b100101 0
1%
#770
0%
#780
b100110 0
1%
#790
0%
#800
b100111 0
1%
#810
0%
#820
b101000 0
1%
#830
0%
#840
b101001 0
1%
#850
0%
#860
b101010 0
1%
#870
0%
#880
b101011 0
1%
#890
0%
#900
b101100 0
1%
#910
0%
#920
b101101 0
1%
#930
0%
#940
b101110 0
1%
#950
0%
#960
b101111 0
1%
#970
0%
#980
b110000 0
1%
#990
0%
#1000
b110001 0
1%
#1010
0%
#1020
b110010 0
1%
#1030
0%
#1040
b110011 0
1%
#1050
0%
#1060
b110100 0
1%
#1070
0%
#1080
b110101 0
1%
#1090
0%
#1100
b110110 0
1%
#1110
0%
#1120
b110111 0
1%
#1130
0%
#1140
b111000 0
1%
#1150
0%
#1160
b111001 0
1%
#1170
0%
#1180
b111010 0
1%
#1190
0%
#1200
b111011 0
1%
#1210
0%
#1220
b111100 0
1%
#1230
0%
#1240
b111101 0
1%
#1250
0%
#1260
b111110 0
1%
#1270
0%
#1280
b111111 0
1%
#1290
0%
#1300
b1000000 0
1%
#1310
0%
#1320
b1000001 0
1%
#1330
0%
#1340
b1000010 0
1%
#1350
0%
#1360
b1000011 0
1%
#1370
0%
#1380
b1000100 0
1%
#1390
0%
#1400
b1000101 0
1%
#1410
0%
#1420
b1000110 0
1%
#1430
0%
#1440
b1000111 0
1%
#1450
0%
#1460
b1001000 0
1%
#1470
0%
#1480
b1001001 0
1%
#1490
0%
#1500
b1001010 0
1%
#1510
0%
#1520
b1001011 0
1%
#1530
0%
#1540
b1001100 0
1%
#1550
0%
#1560
b1001101 0
1%
#1570
0%
#1580
b1001110 0
1%
#1590
0%
#1600
b1001111 0
1%
#1610
0%
#1620
b1010000 0
1%
#1630
0%
#1640
b1010001 0
1%
#1650
0%
#1660
b1010010 0
1%
#1670
0%
#1680
b1010011 0
1%
#1690
0%
#1700
b1010100 0
1%
#1710
0%
#1720
b1010101 0
1%
#1730
0%
#1740
b1010110 0
1%
#1750
0%
#1760
b1010111 0
1%
#1770
0%
#1780
b1011000 0
1%
#1790
0%
#1800
b1011001 0
1%
#1810
0%
#1820
b1011010 0
1%
#1830
0%
#1840
b1011011 0
1%
#1850
0%
#1860
b1011100 0
1%
#1870
0%
#1880
b1011101 0
1%
#1890
0%
#1900
b1011110 0
1%
#1910
0%
#1920
b1011111 0
1%
#1930
0%
#1940
b1100000 0
1%
#1950
0%
#1960
b1100001 0
1%
#1970
0%
#1980
b1100010 0
1%
#1990
0%
#2000
b1100011 0
1%
#2010
0%
#2020
b1100100 0
1%
#2030
0%
#2040
b1100101 0
1%
#2050
0%
#2060
b1100110 0
1%
#2070
0%
#2080
b1100111 0
1%
#2090
0%
#2100
b1101000 0
1%
#2110
0%
#2120
b1101001 0
1%
#2130
0%
#2140
b1101010 0
1%
#2150
0%
#2160
b1101011 0
1%
#2170
0%
#2180
b1101100 0
1%
#2190
0%
#2200
b1101101 0
1%
#2210
0%
#2220
b1101110 0
1%
#2230
0%
#2240
b1101111 0
1%
#2250
0%
#2260
b1110000 0
1%
#2270
0%
#2280
b1110001 0
1%
#2290
0%
#2300
b1110010 0
1%
#2310
0%
#2320
b1110011 0
1%
#2330
0%
#2340
b1110100 0
1%
#2350
0%
#2360
b1110101 0
1%
#2370
0%
#2380
b1110110 0
1%
#2390
0%
#2400
b1110111 0
1%
#2410
0%
#2420
b1111000 0
1%
#2430
0%
#2440
b1111001 0
1%
#2450
0%
#2460
b1111010 0
1%
#2470
0%
#2480
b1111011 0
1%
#2490
0%
#2500
b1111100 0
1%
#2510
0%
#2520
b1111101 0
1%
#2530
0%
#2540
b1111110 0
1%
#2550
0%
#2560
b1111111 0
1%
#2570
0%
#2580
b10000000 0
1%
#2590
0%
#2600
b10000001 0
1%
#2610
0%
#2620
b10000010 0
1%
#2630
0%
#2640
b10000011 0
1%
#2650
0%
#2660
b10000100 0
1%
#2670
0%
#2680
b10000101 0
1%
#2690
0%
#2700
b10000110 0
1%
#2710
0%
#2720
b10000111 0
1%
#2730
0%
#2740
b10001000 0
1%
#2750
0%
#2760
b10001001 0
1%
#2770
0%
#2780
b10001010 0
1%
#2790
0%
#2800
b10001011 0
1%
#2810
0%
#2820
b10001100 0
1%
#2830
0%
#2840
b10001101 0
1%
#2850
0%
#2860
b10001110 0
1%
#2870
0%
#2880
b10001111 0
1%
#2890
0%
#2900
b10010000 0
1%
#2910
0%
#2920
b10010001 0
1%
#2930
0%
#2940
b10010010 0
1%
#2950
0%
#2960
b10010011 0
1%
#2970
0%
#2980
b10010100 0
1%
#2990
0%
#3000
b10010101 0
1%
#3010
0%
#3020
b10010110 0
1%
#3030
0%
#3040
b10010111 0
1%
#3050
0%
#3060
b10011000 0
1%
#3070
0%
#3080
b10011001 0
1%
#3090
0%
#3100
b10011010 0
1%
#3110
0%
#3120
b10011011 0
1%
#3130
0%
#3140
b10011100 0
1%
#3150
0%
#3160
b10011101 0
1%
#3170
0%
#3180
b10011110 0
1%
#3190
0%
#3200
b10011111 0
1%
#3210
0%
#3220
b10100000 0
1%
#3230
0%
#3240
b10100001 0
1%
#3250
0%
#3260
b10100010 0
1%
#3270
0%
#3280
b10100011 0
1%
#3290
0%
#3300
b10100100 0
1%
#3310
0%
#3320
b10100101 0
1%
#3330
0%
#3340
b10100110 0
1%
#3350
0%
#3360
b10100111 0
1%
#3370
0%
#3380
b10101000 0
1%
#3390
0%
#3400
b10101001 0
1%
#3410
0%
#3420
b10101010 0
1%
#3430
0%
#3440
b10101011 0
1%
#3450
0%
#3460
b10101100 0
1%
#3470
0%
#3480
b10101101 0
1%
#3490
0%
#3500
b10101110 0
1%
#3510
0%
#3520
b10101111 0
1%
#3530
0%
#3540
b10110000 0
1%
#3550
0%
#3560
b10110001 0
1%
#3570
0%
#3580
b10110010 0
1%
#3590
0%
#3600
b10110011 0
1%
#3610
0%
#3620
b10110100 0
1%
#3630
0%
#3640
b10110101 0
1%
#3650
0%
#3660
b10110110 0
1%
#3670
0%
#3680
b10110111 0
1%
#3690
0%
#3700
b10111000 0
1%
#3710
0%
#3720
b10111001 0
1%
#3730
0%
#3740
b10111010 0
1%
#3750
0%
#3760
b10111011 0
1%
#3770
0%
#3780
b10111100 0
1%
#3790
0%
#3800
b10111101 0
1%
#3810
0%
#3820
b10111110 0
1%
#3830
0%
#3840
b10111111 0
1%
#3850
0%
#3860
b11000000 0
1%
#3870
0%
#3880
b11000001 0
1%
#3890
0%
#3900
b11000010 0
1%
#3910
0%
#3920
b11000011 0
1%
#3930
0%
#3940
b11000100 0
1%
#3950
0%
#3960
b11000101 0
1%
#3970
0%
#3980
b11000110 0
1%
#3990
0%
#4000
b11000111 0
1%
#4010
0%
#4020
b11001000 0
1%
#4030
0%
#4040
b11001001 0
1%
#4050
0%
#4060
b11001010 0
1%
#4070
0%
#4080
b11001011 0
1%
#4090
0%
#4100
b11001100 0
1%
#4110
0%
#4120
b11001101 0
1%
#4130
0%
#4140
b11001110 0
1%
#4150
0%
#4160
b11001111 0
1%
#4170
0%
#4180
b11010000 0
1%
#4190
0%
#4200
b11010001 0
1%
#4210
0%
#4220
b11010010 0
1%
#4230
0%
#4240
b11010011 0
1%
#4250
0%
#4260
b11010100 0
1%
#4270
0%
#4280
b11010101 0
1%
#4290
0%
#4300
b11010110 0
1%
#4310
0%
#4320
b11010111 0
1%
#4330
0%
#4340
b11011000 0
1%
#4350
0%
#4360
b11011001 0
1%
#4370
0%
#4380
b11011010 0
1%
#4390
0%
#4400
b11011011 0
1%
#4410
0%
#4420
b11011100 0
1%
#4430
0%
#4440
b11011101 0
1%
#4450
0%
#4460
b11011110 0
1%
#4470
0%
#4480
b11011111 0
1%
#4490
0%
#4500
b11100000 0
1%
#4510
0%
#4520
b11100001 0
1%
#4530
0%
#4540
b11100010 0
1%
#4550
0%
#4560
b11100011 0
1%
#4570
0%
#4580
b11100100 0
1%
#4590
0%
#4600
b11100101 0
1%
#4610
0%
#4620
b11100110 0
1%
#4630
0%
#4640
b11100111 0
1%
#4650
0%
#4660
b11101000 0
1%
#4670
0%
#4680
b11101001 0
1%
#4690
0%
#4700
b11101010 0
1%
#4710
0%
#4720
b11101011 0
1%
#4730
0%
#4740
b11101100 0
1%
#4750
0%
#4760
b11101101 0
1%
#4770
0%
#4780
b11101110 0
1%
#4790
0%
#4800
b11101111 0
1%
#4810
0%
#4820
b11110000 0
1%
#4830
0%
#4840
b11110001 0
1%
#4850
0%
#4860
b11110010 0
1%
#4870
0%
#4880
b11110011 0
1%
#4890
0%
#4900
b11110100 0
1%
#4910
0%
#4920
b11110101 0
1%
#4930
0%
#4940
b11110110 0
1%
#4950
0%
#4960
b11110111 0
1%
#4970
0%
#4980
b11111000 0
1%
#4990
0%
#5000
b11111001 0
1%
#5010
0%
#5020
b11111010 0
1%
#5030
0%
#5040
b11111011 0
1%
#5050
0%
#5060
b11111100 0
1%
#5070
0%
#5080
b11111101 0
1%
#5090
0%
#5100
b11111110 0
1%
#5110
0%
#5120
b11111111 0
1%
#5130
0%
#5140
b100000000 0
1%
#5150
0%
#5160
b100000001 0
1%
#5170
0%
#5180
b100000010 0
1%
#5190
0%
#5200
b100000011 0
1%
#5210
0%
#5220
b100000100 0
1%
#5230
0%
#5240
b100000101 0
1%
#5250
0%
#5260
b100000110 0
1%
#5270
0%
#5280
b100000111 0
1%
#5290
0%
#5300
b100001000 0
1%
#5310
0%
#5320
b100001001 0
1%
#5330
0%
#5340
b100001010 0
1%
#5350
0%
#5360
b100001011 0
1%
#5370
0%
#5380
b100001100 0
1%
#5390
0%
#5400
b100001101 0
1%
#5410
0%
#5420
b100001110 0
1%
#5430
0%
#5440
b100001111 0
1%
#5450
0%
#5460
b100010000 0
1%
#5470
0%
#5480
b100010001 0
1%
#5490
0%
#5500
b100010010 0
1%
#5510
0%
#5520
b100010011 0
1%
#5530
0%
#5540
b100010100 0
1%
#5550
0%
#5560
b100010101 0
1%
#5570
0%
#5580
b100010110 0
1%
#5590
0%
#5600
b100010111 0
1%
#5610
0%
#5620
b100011000 0
1%
#5630
0%
#5640
b100011001 0
1%
#5650
0%
#5660
b100011010 0
1%
#5670
0%
#5680
b100011011 0
1%
#5690
0%
#5700
b100011100 0
1%
#5710
0%
#5720
b100011101 0
1%
#5730
0%
#5740
b100011110 0
1%
#5750
0%
#5760
b100011111 0
1%
#5770
0%
#5780
b100100000 0
1%
#5790
0%
#5800
b100100001 0
1%
#5810
0%
#5820
b100100010 0
1%
#5830
0%
#5840
b100100011 0
1%
#5850
0%
#5860
b100100100 0
1%
#5870
0%
#5880
b100100101 0
1%
#5890
0%
#5900
b100100110 0
1%
#5910
0%
#5920
b100100111 0
1%
#5930
0%
#5940
b100101000 0
1%
#5950
0%
#5960
b100101001 0
1%
#5970
0%
#5980
b100101010 0
1%
#5990
0%
#6000
b100101011 0
1%
#6010
0%
#6020
b100101100 0
1%
#6030
0%
#6040
b100101101 0
1%
#6050
0%
#6060
b100101110 0
1%
#6070
0%
#6080
b100101111 0
1%
#6090
0%
#6100
b100110000 0
1%
#6110
0%
#6120
b100110001 0
1%
#6130
0%
#6140
b100110010 0
1%
#6150
0%
#6160
b100110011 0
1%
#6170
0%
#6180
b100110100 0
1%
#6190
0%
#6200
b100110101 0
1%
#6210
0%
#6220
b100110110 0
1%
#6230
0%
#6240
b100110111 0
1%
#6250
0%
#6260
b100111000 0
1%
#6270
0%
#6280
b100111001 0
1%
#6290
0%
#6300
b100111010 0
1%
#6310
0%
#6320
b100111011 0
1%
#6330
0%
#6340
b100111100 0
1%
#6350
0%
#6360
b100111101 0
1%
#6370
0%
#6380
b100111110 0
1%
#6390
0%
#6400
b100111111 0
1%
#6410
0%
#6420
b101000000 0
1%
#6430
0%
#6440
b101000001 0
1%
#6450
0%
#6460
b101000010 0
1%
#6470
0%
#6480
b101000011 0
1%
#6490
0%
#6500
b101000100 0
1%
#6510
0%
#6520
1,
b0 0
1%
#6530
0%
#6540
b1 >
b1 6
0,
b1 0
1%
#6550
0%
#6560
b10 0
1%
#6570
0%
#6580
b11 0
1%
#6590
0%
#6600
b100 0
1%
#6610
0%
#6620
b101 0
1%
#6630
0%
#6640
b110 0
1%
#6650
0%
#6660
b111 0
1%
#6670
0%
#6680
b1000 0
1%
#6690
0%
#6700
b1001 0
1%
#6710
0%
#6720
b1010 0
1%
#6730
0%
#6740
b1011 0
1%
#6750
0%
#6760
b1100 0
1%
#6770
0%
#6780
b1101 0
1%
#6790
0%
#6800
b1110 0
1%
#6810
0%
#6820
b1111 0
1%
#6830
0%
#6840
b10000 0
1%
#6850
0%
#6860
b10001 0
1%
#6870
0%
#6880
b10010 0
1%
#6890
0%
#6900
b10011 0
1%
#6910
0%
#6920
b10100 0
1%
#6930
0%
#6940
b10101 0
1%
#6950
0%
#6960
b10110 0
1%
#6970
0%
#6980
b10111 0
1%
#6990
0%
#7000
b11000 0
1%
#7010
0%
#7020
b11001 0
1%
#7030
0%
#7040
b11010 0
1%
#7050
0%
#7060
b11011 0
1%
#7070
0%
#7080
b11100 0
1%
#7090
0%
#7100
b11101 0
1%
#7110
0%
#7120
b11110 0
1%
#7130
0%
#7140
b11111 0
1%
#7150
0%
#7160
b100000 0
1%
#7170
0%
#7180
b100001 0
1%
#7190
0%
#7200
b100010 0
1%
#7210
0%
#7220
b100011 0
1%
#7230
0%
#7240
b100100 0
1%
#7250
0%
#7260
b100101 0
1%
#7270
0%
#7280
b100110 0
1%
#7290
0%
#7300
b100111 0
1%
#7310
0%
#7320
b101000 0
1%
#7330
0%
#7340
b101001 0
1%
#7350
0%
#7360
b101010 0
1%
#7370
0%
#7380
b101011 0
1%
#7390
0%
#7400
b101100 0
1%
#7410
0%
#7420
b101101 0
1%
#7430
0%
#7440
b101110 0
1%
#7450
0%
#7460
b101111 0
1%
#7470
0%
#7480
b110000 0
1%
#7490
0%
#7500
b110001 0
1%
#7510
0%
#7520
b110010 0
1%
#7530
0%
#7540
b110011 0
1%
#7550
0%
#7560
b110100 0
1%
#7570
0%
#7580
b110101 0
1%
#7590
0%
#7600
b110110 0
1%
#7610
0%
#7620
b110111 0
1%
#7630
0%
#7640
b111000 0
1%
#7650
0%
#7660
b111001 0
1%
#7670
0%
#7680
b111010 0
1%
#7690
0%
#7700
b111011 0
1%
#7710
0%
#7720
b111100 0
1%
#7730
0%
#7740
b111101 0
1%
#7750
0%
#7760
b111110 0
1%
#7770
0%
#7780
b111111 0
1%
#7790
0%
#7800
b1000000 0
1%
#7810
0%
#7820
b1000001 0
1%
#7830
0%
#7840
b1000010 0
1%
#7850
0%
#7860
b1000011 0
1%
#7870
0%
#7880
b1000100 0
1%
#7890
0%
#7900
b1000101 0
1%
#7910
0%
#7920
b1000110 0
1%
#7930
0%
#7940
b1000111 0
1%
#7950
0%
#7960
b1001000 0
1%
#7970
0%
#7980
b1001001 0
1%
#7990
0%
#8000
b1001010 0
1%
#8010
0%
#8020
b1001011 0
1%
#8030
0%
#8040
b1001100 0
1%
#8050
0%
#8060
b1001101 0
1%
#8070
0%
#8080
b1001110 0
1%
#8090
0%
#8100
b1001111 0
1%
#8110
0%
#8120
b1010000 0
1%
#8130
0%
#8140
b1010001 0
1%
#8150
0%
#8160
b1010010 0
1%
#8170
0%
#8180
b1010011 0
1%
#8190
0%
#8200
b1010100 0
1%
#8210
0%
#8220
b1010101 0
1%
#8230
0%
#8240
b1010110 0
1%
#8250
0%
#8260
b1010111 0
1%
#8270
0%
#8280
b1011000 0
1%
#8290
0%
#8300
b1011001 0
1%
#8310
0%
#8320
b1011010 0
1%
#8330
0%
#8340
b1011011 0
1%
#8350
0%
#8360
b1011100 0
1%
#8370
0%
#8380
b1011101 0
1%
#8390
0%
#8400
b1011110 0
1%
#8410
0%
#8420
b1011111 0
1%
#8430
0%
#8440
b1100000 0
1%
#8450
0%
#8460
b1100001 0
1%
#8470
0%
#8480
b1100010 0
1%
#8490
0%
#8500
b1100011 0
1%
#8510
0%
#8520
b1100100 0
1%
#8530
0%
#8540
b1100101 0
1%
#8550
0%
#8560
b1100110 0
1%
#8570
0%
#8580
b1100111 0
1%
#8590
0%
#8600
b1101000 0
1%
#8610
0%
#8620
b1101001 0
1%
#8630
0%
#8640
b1101010 0
1%
#8650
0%
#8660
b1101011 0
1%
#8670
0%
#8680
b1101100 0
1%
#8690
0%
#8700
b1101101 0
1%
#8710
0%
#8720
b1101110 0
1%
#8730
0%
#8740
b1101111 0
1%
#8750
0%
#8760
b1110000 0
1%
#8770
0%
#8780
b1110001 0
1%
#8790
0%
#8800
b1110010 0
1%
#8810
0%
#8820
b1110011 0
1%
#8830
0%
#8840
b1110100 0
1%
#8850
0%
#8860
b1110101 0
1%
#8870
0%
#8880
b1110110 0
1%
#8890
0%
#8900
b1110111 0
1%
#8910
0%
#8920
b1111000 0
1%
#8930
0%
#8940
b1111001 0
1%
#8950
0%
#8960
b1111010 0
1%
#8970
0%
#8980
b1111011 0
1%
#8990
0%
#9000
b1111100 0
1%
#9010
0%
#9020
b1111101 0
1%
#9030
0%
#9040
b1111110 0
1%
#9050
0%
#9060
b1111111 0
1%
#9070
0%
#9080
b10000000 0
1%
#9090
0%
#9100
b10000001 0
1%
#9110
0%
#9120
b10000010 0
1%
#9130
0%
#9140
b10000011 0
1%
#9150
0%
#9160
b10000100 0
1%
#9170
0%
#9180
b10000101 0
1%
#9190
0%
#9200
b10000110 0
1%
#9210
0%
#9220
b10000111 0
1%
#9230
0%
#9240
b10001000 0
1%
#9250
0%
#9260
b10001001 0
1%
#9270
0%
#9280
b10001010 0
1%
#9290
0%
#9300
b10001011 0
1%
#9310
0%
#9320
b10001100 0
1%
#9330
0%
#9340
b10001101 0
1%
#9350
0%
#9360
b10001110 0
1%
#9370
0%
#9380
b10001111 0
1%
#9390
0%
#9400
b10010000 0
1%
#9410
0%
#9420
b10010001 0
1%
#9430
0%
#9440
b10010010 0
1%
#9450
0%
#9460
b10010011 0
1%
#9470
0%
#9480
b10010100 0
1%
#9490
0%
#9500
b10010101 0
1%
#9510
0%
#9520
b10010110 0
1%
#9530
0%
#9540
b10010111 0
1%
#9550
0%
#9560
b10011000 0
1%
#9570
0%
#9580
b10011001 0
1%
#9590
0%
#9600
b10011010 0
1%
#9610
0%
#9620
b10011011 0
1%
#9630
0%
#9640
b10011100 0
1%
#9650
0%
#9660
b10011101 0
1%
#9670
0%
#9680
b10011110 0
1%
#9690
0%
#9700
b10011111 0
1%
#9710
0%
#9720
b10100000 0
1%
#9730
0%
#9740
b10100001 0
1%
#9750
0%
#9760
b10100010 0
1%
#9770
0%
#9780
b10100011 0
1%
#9790
0%
#9800
b10100100 0
1%
#9810
0%
#9820
b10100101 0
1%
#9830
0%
#9840
b10100110 0
1%
#9850
0%
#9860
b10100111 0
1%
#9870
0%
#9880
b10101000 0
1%
#9890
0%
#9900
b10101001 0
1%
#9910
0%
#9920
b10101010 0
1%
#9930
0%
#9940
b10101011 0
1%
#9950
0%
#9960
b10101100 0
1%
#9970
0%
#9980
b10101101 0
1%
#9990
0%
#10000
b10101110 0
1%
#10010
0%
#10020
b10101111 0
1%
#10030
0%
#10040
b10110000 0
1%
#10050
0%
#10060
b10110001 0
1%
#10070
0%
#10080
b10110010 0
1%
#10090
0%
#10100
b10110011 0
1%
#10110
0%
#10120
b10110100 0
1%
#10130
0%
#10140
b10110101 0
1%
#10150
0%
#10160
b10110110 0
1%
#10170
0%
#10180
b10110111 0
1%
#10190
0%
#10200
b10111000 0
1%
#10210
0%
#10220
b10111001 0
1%
#10230
0%
#10240
b10111010 0
1%
#10250
0%
#10260
b10111011 0
1%
#10270
0%
#10280
b10111100 0
1%
#10290
0%
#10300
b10111101 0
1%
#10310
0%
#10320
b10111110 0
1%
#10330
0%
#10340
b10111111 0
1%
#10350
0%
#10360
b11000000 0
1%
#10370
0%
#10380
b11000001 0
1%
#10390
0%
#10400
b11000010 0
1%
#10410
0%
#10420
b11000011 0
1%
#10430
0%
#10440
b11000100 0
1%
#10450
0%
#10460
b11000101 0
1%
#10470
0%
#10480
b11000110 0
1%
